zonotify/__init__.py
zonotify/zonotify.py
zonotify-1.0.5.dist-info/LICENSE
zonotify-1.0.5.dist-info/METADATA
zonotify-1.0.5.dist-info/WHEEL
zonotify-1.0.5.dist-info/top_level.txt
zonotify-1.0.5.dist-info/RECORD
