Metadata-Version: 2.1
Name: zonotify
Version: 1.0.5
Summary: A simple package for sending notifications to Discord and Email in two lines.
Home-page: https://github.com/SidmoGoesBrrr/Zonotify
Author: Siddhant
Author-email: siddhant@zodevelopers.com
Classifier: Programming Language :: Python :: 3
Classifier: License :: OSI Approved :: MIT License
Classifier: Operating System :: OS Independent
Requires-Python: >=3.6
License-File: LICENSE
Requires-Dist: requests
Requires-Dist: webcolors
